koparadigm/__init__.py
koparadigm/koparadigm.py
koparadigm/koparadigm.xlsx
koparadigm-0.10.0.dist-info/LICENSE
koparadigm-0.10.0.dist-info/METADATA
koparadigm-0.10.0.dist-info/WHEEL
koparadigm-0.10.0.dist-info/top_level.txt
koparadigm-0.10.0.dist-info/RECORD
